MANIFEST.in
README.md
meta.json
setup.py
en_john_ner/__init__.py
en_john_ner/meta.json
en_john_ner.egg-info/PKG-INFO
en_john_ner.egg-info/SOURCES.txt
en_john_ner.egg-info/dependency_links.txt
en_john_ner.egg-info/entry_points.txt
en_john_ner.egg-info/not-zip-safe
en_john_ner.egg-info/requires.txt
en_john_ner.egg-info/top_level.txt
en_john_ner/en_john_ner-0.0.0/README.md
en_john_ner/en_john_ner-0.0.0/config.cfg
en_john_ner/en_john_ner-0.0.0/meta.json
en_john_ner/en_john_ner-0.0.0/tokenizer
en_john_ner/en_john_ner-0.0.0/ner/cfg
en_john_ner/en_john_ner-0.0.0/ner/model
en_john_ner/en_john_ner-0.0.0/ner/moves
en_john_ner/en_john_ner-0.0.0/vocab/key2row
en_john_ner/en_john_ner-0.0.0/vocab/lookups.bin
en_john_ner/en_john_ner-0.0.0/vocab/strings.json
en_john_ner/en_john_ner-0.0.0/vocab/vectors
en_john_ner/en_john_ner-0.0.0/vocab/vectors.cfg